schematics_proto3/__init__.py
schematics_proto3/enum.py
schematics_proto3/models.py
schematics_proto3/oneof.py
schematics_proto3/unset.py
schematics_proto3/utils.py
schematics_proto3/types/__init__.py
schematics_proto3/types/base.py
schematics_proto3/types/enum.py
schematics_proto3/types/message.py
schematics_proto3/types/oneof.py
schematics_proto3/types/repeated.py
schematics_proto3/types/wrappers.py
setup_commands/__init__.py
setup_commands/clean.py
setup_commands/protoc.py
setup_commands/pylint.py
schematics_proto3-0.1.3.dist-info/LICENSE
schematics_proto3-0.1.3.dist-info/METADATA
schematics_proto3-0.1.3.dist-info/WHEEL
schematics_proto3-0.1.3.dist-info/top_level.txt
schematics_proto3-0.1.3.dist-info/RECORD
