Metadata-Version: 2.1
Name: schematics-proto3
Version: 0.1.3
Summary: Schematics extension for handling protobuf 3 messages.
Home-page: https://github.com/mlga/schematics-proto3
Author: mlga
Author-email: github@mlga.io
License: MIT
Keywords: protobuf schematics validation serialization input
Platform: any
Requires-Python: >=3.7
Requires-Dist: schematics (~=2.1)
Requires-Dist: protobuf (~=3.9)
Provides-Extra: develop
Requires-Dist: pylint (~=2.3) ; extra == 'develop'
Requires-Dist: pytest (~=5.0) ; extra == 'develop'
Requires-Dist: pytest-cov (~=2.7) ; extra == 'develop'
Requires-Dist: pytest-html (~=1.20) ; extra == 'develop'
Requires-Dist: Sphinx (==3.0.1) ; extra == 'develop'
Requires-Dist: sphinx-rtd-theme (==0.4.3) ; extra == 'develop'
